ipyeoxelements/__init__.py
ipyeoxelements/_version.py
ipyeoxelements/generated.py
ipyeoxelements-1.1.0.dist-info/licenses/LICENSE
ipyeoxelements-1.1.0.dist-info/METADATA
ipyeoxelements-1.1.0.dist-info/WHEEL
ipyeoxelements-1.1.0.dist-info/top_level.txt
ipyeoxelements-1.1.0.dist-info/RECORD
