Metadata-Version: 2.4
Name: ipyeoxelements
Version: 1.1.0
Summary: Jupyter notebook wrapper for EOxElements web components
Author-email: EOX <silvester.pari@eox.at>
License-Expression: MIT
Project-URL: Homepage, https://github.com/EOX-A/EOxElements-Jupyter
Project-URL: Issues, https://github.com/EOX-A/EOxElements-Jupyter/issues
Requires-Python: >=3.8
License-File: LICENSE
Requires-Dist: anywidget>=0.9.0
Requires-Dist: ipywidgets>=8.0.0
Requires-Dist: traitlets
Provides-Extra: dev
Requires-Dist: build; extra == "dev"
Requires-Dist: twine; extra == "dev"
Requires-Dist: requests; extra == "dev"
Requires-Dist: watchdog; extra == "dev"
Dynamic: license-file
